{
    "defaultStacks": ["frontend"],
    "packages":{
        "onward":{
            "type":"autoscaling",
            "data":{
                "secondsToWait":1200,
                "port":18080,
                "healthcheckGrace":20,
                "warmupGrace":30,
                "bucket":"aws-frontend-artifacts",
                "healthcheck_paths":[
                    "/management/healthcheck"
                ]
            }
        }

    },
    "recipes":{
        "default":{
            "depends" : ["artifactUpload", "deploy"]
        },
        "deploy":{
            "actionsBeforeApp": ["onward.deploy"]
        },
        "artifactUpload":{
            "actionsBeforeApp": ["onward.uploadArtifacts"]
        }
    }
}
